README.rst
setup.py
file2py/__init__.py
file2py/conv.py
file2py/templates.py
file2py/tool.py
file2py.egg-info/PKG-INFO
file2py.egg-info/SOURCES.txt
file2py.egg-info/dependency_links.txt
file2py.egg-info/top_level.txt
scripts/file2py
scripts/image2py