Metadata-Version: 1.1
Name: file2py
Version: 0.2.2
Summary: Allows to include/manage binary files in python source file.
Home-page: https://github.com/kAlmAcetA/file2py
Author: Krzysztof Warunek
Author-email: kalmaceta@gmail.com
License: MIT
Keywords: binary,converter,pyside,qt,pyqt,file2py
Platform: UNKNOWN
Classifier: License :: OSI Approved :: MIT License
Classifier: Programming Language :: Python :: 3
Classifier: Programming Language :: Python :: 2
Classifier: Operating System :: POSIX
Classifier: Development Status :: 3 - Alpha
